Metadata-Version: 1.1
Name: s17.portlets
Version: 1.0b2
Summary: User Profile, Birthdays and White Pages portlets for a user or person.
Home-page: https://github.com/simplesconsultoria/s17.portlets
Author: Simples Consultoria
Author-email: products@simplesconsultoria.com.br
License: UNKNOWN
Keywords: user person profile birthdays search portlet
Platform: UNKNOWN
Classifier: Development Status :: 4 - Beta
Classifier: Environment :: Web Environment
Classifier: Framework :: Plone
Classifier: Framework :: Plone :: 4.2
Classifier: Framework :: Plone :: 4.3
Classifier: Intended Audience :: Developers
Classifier: License :: OSI Approved :: GNU General Public License v2 (GPLv2)
Classifier: Operating System :: OS Independent
Classifier: Programming Language :: Python
Classifier: Programming Language :: Python :: 2.6
Classifier: Programming Language :: Python :: 2.7
Classifier: Topic :: Office/Business
Classifier: Topic :: Internet :: WWW/HTTP
Classifier: Topic :: Internet :: WWW/HTTP :: Dynamic Content
Classifier: Topic :: Software Development :: Libraries :: Python Modules
